{
    "AS_Image_e52e8cd9928f4a0f82a5c7aedd668f0a": {
        "id": "AS_Image_e52e8cd9928f4a0f82a5c7aedd668f0a",
        "type": "ACTION_SEQUENCE",
        "params": [{
            "datatype": "collection",
            "name": "eventobject"
        }, {
            "datatype": "string",
            "name": "x"
        }, {
            "datatype": "string",
            "name": "y"
        }],
        "contextObj": {
            "name": "frmReceiveSTOShip",
            "type": "forms",
            "platform": null,
            "KUID": "c27e0f38e6b94bb8be14110013bea769"
        },
        "language": "js",
        "actions": [{
            "id": "NAVIGATE_TO_FORM__ide_onTouchStart_e5d2a2d3ab7e40829e49a8f255c07c1d",
            "type": "NAVIGATE_TO_FORM",
            "formId": "frmMenuMain",
            "formKUID": "da976575439d47b28d3f7f3f0e725888",
            "mappings": {},
            "mappingsOrder": [],
            "parentId": "",
            "callbackType": null,
            "enableMappingEditor": true,
            "package": ""
        }]
    }
}